plainlog/__init__.py
plainlog/__version__.py
plainlog/_dev.py
plainlog/_env.py
plainlog/_frames.py
plainlog/_logger.py
plainlog/_recattrs.py
plainlog/_utils.py
plainlog/configure.py
plainlog/formatters.py
plainlog/handlers.py
plainlog/processors.py
plainlog/py.typed
plainlog/std.py
plainlog/warnings.py
plainlog-0.2.0.dist-info/METADATA
plainlog-0.2.0.dist-info/WHEEL
plainlog-0.2.0.dist-info/licenses/LICENSES/Apache-2.0.txt
plainlog-0.2.0.dist-info/licenses/LICENSES/MIT.txt
plainlog-0.2.0.dist-info/RECORD
