Metadata-Version: 2.4
Name: plainlog
Version: 0.2.0
Summary: Logging made simple and easy.
Project-URL: Documentation, https://github.com/tds333/plainlog#readme
Project-URL: Issues, https://github.com/tds333/plainlog/issues
Project-URL: Source, https://github.com/tds333/plainlog
Author-email: Wolfgang Langner <tds333@mailbox.org>
License-Expression: Apache-2.0 OR MIT
License-File: LICENSES/Apache-2.0.txt
License-File: LICENSES/MIT.txt
Classifier: Development Status :: 4 - Beta
Classifier: Intended Audience :: Developers
Classifier: License :: OSI Approved :: Apache Software License
Classifier: License :: OSI Approved :: MIT License
Classifier: Natural Language :: English
Classifier: Operating System :: OS Independent
Classifier: Programming Language :: Python
Classifier: Programming Language :: Python :: 3.9
Classifier: Programming Language :: Python :: 3.10
Classifier: Programming Language :: Python :: 3.11
Classifier: Programming Language :: Python :: 3.12
Classifier: Programming Language :: Python :: 3.13
Classifier: Programming Language :: Python :: 3.14
Classifier: Programming Language :: Python :: Implementation :: CPython
Classifier: Programming Language :: Python :: Implementation :: PyPy
Classifier: Topic :: System :: Logging
Requires-Python: >=3.9
